{
  "Украинский государственный университет железнодорожного транспорта": ["Факультет Строительный", "Факультет Механико - энергетический", "Факультет Экономический", "Факультет Управление процесамми перевозок"],
  "Харьковский национальный университет радиоэлектроники": ["Факультет компьютерных наук", "Факультет автоматики и компьютеризированных технологий", "Факультет компьютерной инженерии и управления", "Факультет инфокоммуникаций"],
  "Киевский национальный университет строительства и архитектуры (КНУСА)": ["Строительный факультет", "Архитектурный факультет", "Строительно - технологический факультет", "Факультет урбанистики и территориального планирования"],
  "Государственный университет инфраструктуры и технологий": ["Факультет судовождения", "Факультет эксплуатации технических систем на водном транспорте", "Факультет управления и технологий", "Юридический факультет"],
  "Государственный университет телекоммуникаций": ["Факультет Компьютерная инженерия", "Факультет Инженерия программного обеспечения", "факультет Социология"],
  "Государственный университет экономики и технологий": ["Факультет информационных технологий", "Юридический факультет", "Экономический факультет"],
  "Днепровский государственный технический университет": ["факультет механический", "факультет энергетический", "факультет металургический", "факультет электроники и компьютерной техники", "факультет менеджмента", "факультет экономики", "факультет социологии и филологии"],
  "Ивано - Франковский национальный технический университет нефти и газа": ["факультет экономики и менеджмента", "факультет инженерной механики", "факультет информационных технологий", "факультет нефтегазовой инженерии"],
  "Киевский национальный университет имени Тараса Шевченко": ["экономический факультет", "факультет кибернетики", "механико - математический факультет", "факультет радиофизики", "электроники и компьютерных систем", "факультет социологии физический факультет", "философский факультет", "химический факультет", "юридический факультет", "факультет психологии"],
  "Киевский национальный университет технологий и дизайна": ["Факультет индустрии моды", "Факультет мехатроники и компьютерных технологий", "Факультет дизайна", "Факультет экономики и бизнеса", "Факультет предпринимательства и права"],
  "Кропивницкий национальный технический университет": ["Факультет сельскохозяйственного машиностроения", "Факультет автоматики и энергетики", "Механико - технологический факультет", "Факультет проектирования и эксплуатации машин"],
  "Луцкий национальный технический университет": ["Факультет бизнеса", "Технологический факультет", "Факультет строительства и дизайна", "Факультет финансов, учета, лингвистики и права"],
  "Львовский национальный аграрный университет": ["ЭкоФакультет строительства и архитектуры", "Эномический факультет", "Землеустроительный факультет", "Факультет механики и энергетики"],
  "Национальный авиационный университет": ["Аэрокосмический факультет", "Факультет лингвистики и социальных коммуникаций", "Факультет аэронавигации, электроники и телекоммуникации", "Факультет архитектуры, строительства и дизайна", "Факультет экологической безопасности, инженерии и технологий", "Факультет кибербезопасности, компьютерной и программной инженерии", "Факультет международных отношений", "Юридический факультет"],
  "Национальный лесотехнический университет Украины": ["факультет лесного и садово - паркового хозяйства", "Факультет инженерной механики, автоматизации и компьютерно - интегрированных технологий", "Факультет деревообрабатывающих технологий и дизайна", "Факультет экологической экономики и менеджмента"],
  "Национальный технический университет «Харьковский политехнический институт»": ["Факультет химических технологий и инженерии", "факультет экономики, менеджмента и международного бизнеса", "Факультет компьютерных и информационных технологий", "Факультет компьютерных наук и программной инженерии", "Факультет социально - гуманитарных технологий", "Факультет международного образования"],
  "Национальный университет 'Одесская морская академия'": ["Факультет судовождения", "Факультет морских перевозок и технологий", "Судомеханический факультет", "Факультет морского права и менеджмента"],
  "Национальный университет «Львовская политехника»": ["Факультет архитектуры и дизайна", "Факультет строительства и инженерных систем", "факультет геодезии", "факультет гуманитарных и социальных наук"],
  "Национальный университет биоресурсов и природопользования Украины": ["Факультет землеустройства", "Юридический факультет", "Факультет конструирования и дизайна", "Факультет ветеринарной медицины", "Факультет защиты растений, биотехнологий и экологии", "Факультет животноводства и водных биоресурсов", "Факультет пищевых технологий и управления качеством продукции", "Факультет аграрного менеджмента"],
  "Национальный университет водного хозяйства и природопользования": ["факультет водного хозяйства и природообустройства", "факультет автоматики, кибернетики и вычислительной техники", "факультет строительства и архитектуры"],
  "Национальный университет кораблестроения имени адмирала Макарова": ["Факультет экономики моря", "Факультет морского права", "Факультет экологической и техногенной безопасности", "Факультет морской инфраструктуры"],
  "Национальный университет пищевых технологий": ["Факультет автоматизации и компьютерных систем", "Факультет биотехнологии и экологического контроля", "Факультет гостинично - ресторанного и туристического бизнеса"]

}
